[
  {"model": "drinks.drink", "pk": 1, "fields": {"name": "Эспрессо", "description": "Классика", "strength": 5, "sweetness": 1, "bitterness": 5, "temperature": "hot", "caffeine_free": false, "milk_based": false}},
  {"model": "drinks.drink", "pk": 2, "fields": {"name": "Доппио", "description": "Двойной", "strength": 5, "sweetness": 1, "bitterness": 5, "temperature": "hot", "caffeine_free": false, "milk_based": false}},
  {"model": "drinks.drink", "pk": 3, "fields": {"name": "Ристретто", "description": "Короткий", "strength": 5, "sweetness": 1, "bitterness": 5, "temperature": "hot", "caffeine_free": false, "milk_based": false}},
  {"model": "drinks.drink", "pk": 4, "fields": {"name": "Американо", "description": "Вода+эспрессо", "strength": 4, "sweetness": 1, "bitterness": 4, "temperature": "hot", "caffeine_free": false, "milk_based": false}},
  {"model": "drinks.drink", "pk": 5, "fields": {"name": "Лонг блэк", "description": "Вода сверху", "strength": 4, "sweetness": 1, "bitterness": 4, "temperature": "hot", "caffeine_free": false, "milk_based": false}},
  {"model": "drinks.drink", "pk": 6, "fields": {"name": "Капучино", "description": "Кофе+молоко", "strength": 3, "sweetness": 2, "bitterness": 3, "temperature": "hot", "caffeine_free": false, "milk_based": true}},
  {"model": "drinks.drink", "pk": 7, "fields": {"name": "Латте", "description": "Много молока", "strength": 2, "sweetness": 3, "bitterness": 2, "temperature": "hot", "caffeine_free": false, "milk_based": true}},
  {"model": "drinks.drink", "pk": 8, "fields": {"name": "Флэт уайт", "description": "Двойной эспрессо", "strength": 4, "sweetness": 2, "bitterness": 3, "temperature": "hot", "caffeine_free": false, "milk_based": true}},
  {"model": "drinks.drink", "pk": 9, "fields": {"name": "Раф", "description": "Со сливками", "strength": 3, "sweetness": 4, "bitterness": 2, "temperature": "hot", "caffeine_free": false, "milk_based": true}},
  {"model": "drinks.drink", "pk": 10, "fields": {"name": "Мокко", "description": "С шоколадом", "strength": 3, "sweetness": 5, "bitterness": 2, "temperature": "hot", "caffeine_free": false, "milk_based": true}},
  {"model": "drinks.drink", "pk": 11, "fields": {"name": "Макиато", "description": "Пятно молока", "strength": 4, "sweetness": 2, "bitterness": 4, "temperature": "hot", "caffeine_free": false, "milk_based": true}},
  {"model": "drinks.drink", "pk": 12, "fields": {"name": "Кортадо", "description": "Эспрессо+молоко", "strength": 4, "sweetness": 2, "bitterness": 3, "temperature": "hot", "caffeine_free": false, "milk_based": true}},
  {"model": "drinks.drink", "pk": 13, "fields": {"name": "Глясе", "description": "С мороженым", "strength": 3, "sweetness": 5, "bitterness": 2, "temperature": "cold", "caffeine_free": false, "milk_based": true}},
  {"model": "drinks.drink", "pk": 14, "fields": {"name": "Фраппе", "description": "Ледяной", "strength": 3, "sweetness": 4, "bitterness": 2, "temperature": "cold", "caffeine_free": false, "milk_based": true}},
  {"model": "drinks.drink", "pk": 15, "fields": {"name": "Айс латте", "description": "Холодный", "strength": 2, "sweetness": 3, "bitterness": 2, "temperature": "cold", "caffeine_free": false, "milk_based": true}},
  {"model": "drinks.drink", "pk": 16, "fields": {"name": "Нитрo", "description": "Азотный", "strength": 4, "sweetness": 2, "bitterness": 3, "temperature": "cold", "caffeine_free": false, "milk_based": false}},
  {"model": "drinks.drink", "pk": 17, "fields": {"name": "Декаф эспрессо", "description": "Без кофеина", "strength": 5, "sweetness": 1, "bitterness": 5, "temperature": "hot", "caffeine_free": true, "milk_based": false}},
  {"model": "drinks.drink", "pk": 18, "fields": {"name": "Декаф латте", "description": "Без кофеина", "strength": 2, "sweetness": 3, "bitterness": 2, "temperature": "hot", "caffeine_free": true, "milk_based": true}},
  {"model": "drinks.drink", "pk": 19, "fields": {"name": "Декаф капучино", "description": "Без кофеина", "strength": 3, "sweetness": 2, "bitterness": 3, "temperature": "hot", "caffeine_free": true, "milk_based": true}},
  {"model": "drinks.drink", "pk": 20, "fields": {"name": "Зеленый чай", "description": "Свежий", "strength": 1, "sweetness": 1, "bitterness": 3, "temperature": "hot", "caffeine_free": false, "milk_based": false}},
  {"model": "drinks.drink", "pk": 21, "fields": {"name": "Черный чай", "description": "Крепкий", "strength": 3, "sweetness": 1, "bitterness": 4, "temperature": "hot", "caffeine_free": false, "milk_based": false}},
  {"model": "drinks.drink", "pk": 22, "fields": {"name": "Чай латте", "description": "Чай+молоко", "strength": 2, "sweetness": 3, "bitterness": 2, "temperature": "hot", "caffeine_free": false, "milk_based": true}},
  {"model": "drinks.drink", "pk": 23, "fields": {"name": "Матча", "description": "Японский", "strength": 2, "sweetness": 2, "bitterness": 4, "temperature": "hot", "caffeine_free": false, "milk_based": false}},
  {"model": "drinks.drink", "pk": 24, "fields": {"name": "Матча латте", "description": "С молоком", "strength": 2, "sweetness": 3, "bitterness": 3, "temperature": "hot", "caffeine_free": false, "milk_based": true}},
  {"model": "drinks.drink", "pk": 25, "fields": {"name": "Каркаде", "description": "Из hibiscus", "strength": 1, "sweetness": 2, "bitterness": 1, "temperature": "hot", "caffeine_free": true, "milk_based": false}},
  {"model": "drinks.drink", "pk": 26, "fields": {"name": "Ройбуш", "description": "Травяной", "strength": 1, "sweetness": 2, "bitterness": 1, "temperature": "hot", "caffeine_free": true, "milk_based": false}},
  {"model": "drinks.drink", "pk": 27, "fields": {"name": "Имбирный чай", "description": "Согревает", "strength": 2, "sweetness": 2, "bitterness": 2, "temperature": "hot", "caffeine_free": true, "milk_based": false}},
  {"model": "drinks.drink", "pk": 28, "fields": {"name": "Мятный чай", "description": "Освежает", "strength": 1, "sweetness": 1, "bitterness": 1, "temperature": "hot", "caffeine_free": true, "milk_based": false}},
  {"model": "drinks.drink", "pk": 29, "fields": {"name": "Ромашка", "description": "Успокаивает", "strength": 1, "sweetness": 1, "bitterness": 1, "temperature": "hot", "caffeine_free": true, "milk_based": false}},
  {"model": "drinks.drink", "pk": 30, "fields": {"name": "Лимонад", "description": "Классический", "strength": 1, "sweetness": 4, "bitterness": 1, "temperature": "cold", "caffeine_free": true, "milk_based": false}},
  {"model": "drinks.drink", "pk": 31, "fields": {"name": "Мохито", "description": "С мятой", "strength": 1, "sweetness": 3, "bitterness": 1, "temperature": "cold", "caffeine_free": true, "milk_based": false}},
  {"model": "drinks.drink", "pk": 32, "fields": {"name": "Имбирный эль", "description": "Пряный", "strength": 1, "sweetness": 4, "bitterness": 2, "temperature": "cold", "caffeine_free": true, "milk_based": false}},
  {"model": "drinks.drink", "pk": 33, "fields": {"name": "Смузи клубничный", "description": "С ягодами", "strength": 1, "sweetness": 5, "bitterness": 1, "temperature": "cold", "caffeine_free": true, "milk_based": false}},
  {"model": "drinks.drink", "pk": 34, "fields": {"name": "Смузи банановый", "description": "С йогуртом", "strength": 1, "sweetness": 5, "bitterness": 1, "temperature": "cold", "caffeine_free": true, "milk_based": true}},
  {"model": "drinks.drink", "pk": 35, "fields": {"name": "Фреш апельсин", "description": "Свежий", "strength": 1, "sweetness": 5, "bitterness": 2, "temperature": "cold", "caffeine_free": true, "milk_based": false}},
  {"model": "drinks.drink", "pk": 36, "fields": {"name": "Фреш грейпфрут", "description": "Кислый", "strength": 1, "sweetness": 2, "bitterness": 4, "temperature": "cold", "caffeine_free": true, "milk_based": false}},
  {"model": "drinks.drink", "pk": 37, "fields": {"name": "Какао", "description": "Детский", "strength": 1, "sweetness": 5, "bitterness": 1, "temperature": "hot", "caffeine_free": false, "milk_based": true}},
  {"model": "drinks.drink", "pk": 38, "fields": {"name": "Горячий шоколад", "description": "Сливки+шоколад", "strength": 1, "sweetness": 5, "bitterness": 2, "temperature": "hot", "caffeine_free": false, "milk_based": true}},
  {"model": "drinks.drink", "pk": 39, "fields": {"name": "Шоколад мятный", "description": "С мятой", "strength": 1, "sweetness": 5, "bitterness": 2, "temperature": "hot", "caffeine_free": false, "milk_based": true}},
  {"model": "drinks.drink", "pk": 40, "fields": {"name": "Сливочный пончик", "description": "Кофе+сливки", "strength": 2, "sweetness": 5, "bitterness": 1, "temperature": "hot", "caffeine_free": false, "milk_based": true}},
  {"model": "drinks.drink", "pk": 41, "fields": {"name": "Медовый раф", "description": "С медом", "strength": 3, "sweetness": 5, "bitterness": 2, "temperature": "hot", "caffeine_free": false, "milk_based": true}},
  {"model": "drinks.drink", "pk": 42, "fields": {"name": "Кокосовый латте", "description": "На кокосовом", "strength": 2, "sweetness": 4, "bitterness": 2, "temperature": "hot", "caffeine_free": false, "milk_based": true}},
  {"model": "drinks.drink", "pk": 43, "fields": {"name": "Миндальный латте", "description": "На миндальном", "strength": 2, "sweetness": 3, "bitterness": 2, "temperature": "hot", "caffeine_free": false, "milk_based": true}},
  {"model": "drinks.drink", "pk": 44, "fields": {"name": "Овсяный капучино", "description": "На овсяном", "strength": 3, "sweetness": 3, "bitterness": 3, "temperature": "hot", "caffeine_free": false, "milk_based": true}},
  {"model": "drinks.drink", "pk": 45, "fields": {"name": "Тыквенный латте", "description": "Сезонный", "strength": 2, "sweetness": 5, "bitterness": 1, "temperature": "hot", "caffeine_free": false, "milk_based": true}},
  {"model": "drinks.drink", "pk": 46, "fields": {"name": "Карамельный макиато", "description": "С карамелью", "strength": 4, "sweetness": 5, "bitterness": 3, "temperature": "hot", "caffeine_free": false, "milk_based": true}},
  {"model": "drinks.drink", "pk": 47, "fields": {"name": "Ванильный капучино", "description": "С ванилью", "strength": 3, "sweetness": 4, "bitterness": 3, "temperature": "hot", "caffeine_free": false, "milk_based": true}},
  {"model": "drinks.drink", "pk": 48, "fields": {"name": "Лесной орех", "description": "С сиропом", "strength": 3, "sweetness": 4, "bitterness": 3, "temperature": "hot", "caffeine_free": false, "milk_based": true}},
  {"model": "drinks.drink", "pk": 49, "fields": {"name": "Имбирный латте", "description": "Пряный", "strength": 2, "sweetness": 4, "bitterness": 2, "temperature": "hot", "caffeine_free": false, "milk_based": true}},
  {"model": "drinks.drink", "pk": 50, "fields": {"name": "Бейлис латте", "description": "Алкогольный", "strength": 2, "sweetness": 5, "bitterness": 2, "temperature": "hot", "caffeine_free": false, "milk_based": true}},
  {"model": "drinks.drink", "pk": 51, "fields": {"name": "Айс матча", "description": "Холодная", "strength": 2, "sweetness": 2, "bitterness": 4, "temperature": "cold", "caffeine_free": false, "milk_based": false}},
  {"model": "drinks.drink", "pk": 52, "fields": {"name": "Айс матча латте", "description": "Со льдом", "strength": 2, "sweetness": 3, "bitterness": 3, "temperature": "cold", "caffeine_free": false, "milk_based": true}},
  {"model": "drinks.drink", "pk": 53, "fields": {"name": "Холодный капучино", "description": "Ледяной", "strength": 3, "sweetness": 3, "bitterness": 3, "temperature": "cold", "caffeine_free": false, "milk_based": true}},
  {"model": "drinks.drink", "pk": 54, "fields": {"name": "Айс мокко", "description": "С шоколадом", "strength": 3, "sweetness": 5, "bitterness": 2, "temperature": "cold", "caffeine_free": false, "milk_based": true}},
  {"model": "drinks.drink", "pk": 55, "fields": {"name": "Айс раф", "description": "Холодный", "strength": 3, "sweetness": 4, "bitterness": 2, "temperature": "cold", "caffeine_free": false, "milk_based": true}},
  {"model": "drinks.drink", "pk": 56, "fields": {"name": "Фраппе шоколадный", "description": "Молочный", "strength": 1, "sweetness": 5, "bitterness": 1, "temperature": "cold", "caffeine_free": false, "milk_based": true}},
  {"model": "drinks.drink", "pk": 57, "fields": {"name": "Фраппе карамельный", "description": "Ледяной", "strength": 1, "sweetness": 5, "bitterness": 1, "temperature": "cold", "caffeine_free": false, "milk_based": true}},
  {"model": "drinks.drink", "pk": 58, "fields": {"name": "Смузи манго", "description": "Тропический", "strength": 1, "sweetness": 5, "bitterness": 1, "temperature": "cold", "caffeine_free": true, "milk_based": false}},
  {"model": "drinks.drink", "pk": 59, "fields": {"name": "Смузи малина", "description": "Кисло-сладкий", "strength": 1, "sweetness": 4, "bitterness": 2, "temperature": "cold", "caffeine_free": true, "milk_based": false}},
  {"model": "drinks.drink", "pk": 60, "fields": {"name": "Смузи черника", "description": "Ягодный", "strength": 1, "sweetness": 4, "bitterness": 2, "temperature": "cold", "caffeine_free": true, "milk_based": false}},
  {"model": "drinks.drink", "pk": 61, "fields": {"name": "Лимонад малина", "description": "Ягодный", "strength": 1, "sweetness": 4, "bitterness": 1, "temperature": "cold", "caffeine_free": true, "milk_based": false}},
  {"model": "drinks.drink", "pk": 62, "fields": {"name": "Лимонад клубника", "description": "Свежий", "strength": 1, "sweetness": 4, "bitterness": 1, "temperature": "cold", "caffeine_free": true, "milk_based": false}},
  {"model": "drinks.drink", "pk": 63, "fields": {"name": "Лимонад манго", "description": "Экзотический", "strength": 1, "sweetness": 4, "bitterness": 1, "temperature": "cold", "caffeine_free": true, "milk_based": false}},
  {"model": "drinks.drink", "pk": 64, "fields": {"name": "Чай холодный", "description": "Айс ти", "strength": 2, "sweetness": 3, "bitterness": 3, "temperature": "cold", "caffeine_free": false, "milk_based": false}},
  {"model": "drinks.drink", "pk": 65, "fields": {"name": "Чай персик", "description": "Фруктовый", "strength": 1, "sweetness": 4, "bitterness": 1, "temperature": "cold", "caffeine_free": false, "milk_based": false}},
  {"model": "drinks.drink", "pk": 66, "fields": {"name": "Чай ягода", "description": "Ягодный", "strength": 1, "sweetness": 4, "bitterness": 1, "temperature": "cold", "caffeine_free": false, "milk_based": false}},
  {"model": "drinks.drink", "pk": 67, "fields": {"name": "Шот эспрессо", "description": "30 мл", "strength": 5, "sweetness": 1, "bitterness": 5, "temperature": "hot", "caffeine_free": false, "milk_based": false}},
  {"model": "drinks.drink", "pk": 68, "fields": {"name": "Романо", "description": "С лимоном", "strength": 4, "sweetness": 2, "bitterness": 4, "temperature": "hot", "caffeine_free": false, "milk_based": false}},
  {"model": "drinks.drink", "pk": 69, "fields": {"name": "Кон панна", "description": "Со сливками", "strength": 4, "sweetness": 3, "bitterness": 4, "temperature": "hot", "caffeine_free": false, "milk_based": true}},
  {"model": "drinks.drink", "pk": 70, "fields": {"name": "Бреве", "description": "Сливки+молоко", "strength": 3, "sweetness": 3, "bitterness": 3, "temperature": "hot", "caffeine_free": false, "milk_based": true}},
  {"model": "drinks.drink", "pk": 71, "fields": {"name": "Аффогато", "description": "Эспрессо+мороженое", "strength": 4, "sweetness": 5, "bitterness": 4, "temperature": "cold", "caffeine_free": false, "milk_based": true}},
  {"model": "drinks.drink", "pk": 72, "fields": {"name": "Эспрессо тоник", "description": "С тоником", "strength": 3, "sweetness": 3, "bitterness": 3, "temperature": "cold", "caffeine_free": false, "milk_based": false}},
  {"model": "drinks.drink", "pk": 73, "fields": {"name": "Оранж американо", "description": "С апельсином", "strength": 3, "sweetness": 3, "bitterness": 3, "temperature": "hot", "caffeine_free": false, "milk_based": false}},
  {"model": "drinks.drink", "pk": 74, "fields": {"name": "Лимонад с чаем", "description": "Смесь", "strength": 1, "sweetness": 4, "bitterness": 2, "temperature": "cold", "caffeine_free": false, "milk_based": false}},
  {"model": "drinks.drink", "pk": 75, "fields": {"name": "Смузи шпинат", "description": "Зеленый", "strength": 1, "sweetness": 3, "bitterness": 2, "temperature": "cold", "caffeine_free": true, "milk_based": false}}
]